hsluv.py
hsluv_restored-5.0.2.post1.dist-info/LICENSE.txt
hsluv_restored-5.0.2.post1.dist-info/METADATA
hsluv_restored-5.0.2.post1.dist-info/WHEEL
hsluv_restored-5.0.2.post1.dist-info/top_level.txt
hsluv_restored-5.0.2.post1.dist-info/RECORD
