Metadata-Version: 2.1
Name: hsluv-restored
Version: 5.0.2.post1
Summary: Human-friendly HSL
Home-page: https://www.hsluv.org
Author-email: alexei@boronine.com
License: MIT
Keywords: color hsl cie cieluv colorwheel hsluv hpluv
Platform: UNKNOWN
Classifier: Development Status :: 5 - Production/Stable
Classifier: Intended Audience :: Developers
Classifier: License :: OSI Approved :: MIT License
Classifier: Operating System :: OS Independent
Classifier: Topic :: Software Development
Classifier: Programming Language :: Python :: 3
Classifier: Programming Language :: Python :: 3.6
Classifier: Programming Language :: Python :: 3.7
Classifier: Programming Language :: Python :: 3.8
Classifier: Programming Language :: Python :: 3.9
Classifier: Programming Language :: Python :: 3 :: Only
Requires-Python: >=3.6
License-File: LICENSE.txt
